LICENSE
MANIFEST.in
README.rst
requirements.txt
setup.py
setuplib.py
Django_Sublime_Scroll.egg-info/PKG-INFO
Django_Sublime_Scroll.egg-info/SOURCES.txt
Django_Sublime_Scroll.egg-info/dependency_links.txt
Django_Sublime_Scroll.egg-info/top_level.txt
django_sublime_scroll.egg-info/SOURCES.txt
sublime_scroll/__init__.py
sublime_scroll/__init__.pyc
sublime_scroll/models.pyc
sublime_scroll/settings.py
sublime_scroll/settings.pyc
sublime_scroll/static/coffee/sublime-scroll.coffee
sublime_scroll/static/js/sublime-scroll.js
sublime_scroll/templates/sublime_scroll/include.html
sublime_scroll/templatetags/__init__.py
sublime_scroll/templatetags/__init__.pyc
sublime_scroll/templatetags/sublime_scroll_tags.py
sublime_scroll/templatetags/sublime_scroll_tags.pyc