Metadata-Version: 1.0
Name: django-sublime-scroll
Version: 0.2.2
Summary: Sublime Text 2 editor style scroll bars.
Home-page: https://github.com/demux/django-sublime-scroll
Author: Arnar Yngvason
Author-email: arnar1@gmail.com
License: BSD License
Platform: OS Independent
Classifier: Development Status :: 4 - Beta
Classifier: Environment :: Web Environment
Classifier: Framework :: Django
Classifier: Intended Audience :: Developers
Classifier: License :: OSI Approved :: BSD License
Classifier: Operating System :: OS Independent
Classifier: Programming Language :: Python
Classifier: Topic :: Internet :: WWW/HTTP :: Dynamic Content
Classifier: Topic :: Software Development
